{"gender":"female","name":{"title":"Miss","first":"Avery","last":"Brown"},"email":"avery.brown@example.com","login":{"username":"organickoala848","uuid":"dKJox0C4QAq4JzOFGBXA3g==","isloggedin":true},"picture":{"large":"https://randomuser.me/api/portraits/women/43.jpg","medium":"https://randomuser.me/api/portraits/med/women/43.jpg","thumbnail":"https://randomuser.me/api/portraits/thumb/women/43.jpg"},"location":{"street":{"number":5326,"name":"Maple Ave"},"city":"South River","state":"Nunavut","country":"Canada","postcode":"S9Q 4L8","coordinates":{"latitude":-19.6628,"longitude":-153.8058},"timezone":{"offset":"+5:30","description":"Bombay, Calcutta, Madras, New Delhi"}},"isactive":true}