{"gender":"female","name":{"title":"Mrs","first":"Fatima","last":"Montero"},"email":"fatima.montero@example.com","login":{"username":"goldenlion521","uuid":"fKi1Kg1ASYWfyz5N8Z4X8w==","isloggedin":true},"picture":{"large":"https://randomuser.me/api/portraits/women/18.jpg","medium":"https://randomuser.me/api/portraits/med/women/18.jpg","thumbnail":"https://randomuser.me/api/portraits/thumb/women/18.jpg"},"location":{"street":{"number":9038,"name":"Calle de Atocha"},"city":"Móstoles","state":"Andalucía","country":"Spain","postcode":64610,"coordinates":{"latitude":-25.6703,"longitude":53.2065},"timezone":{"offset":"-3:30","description":"Newfoundland"}},"isactive":true}