{"gender":"male","name":{"title":"Mr","first":"علی","last":"گلشن"},"email":"aaly.glshn@example.com","login":{"username":"redlion527","uuid":"MqzjC8vnTAmXUMU2jmG0hA==","isloggedin":true},"picture":{"large":"https://randomuser.me/api/portraits/men/36.jpg","medium":"https://randomuser.me/api/portraits/med/men/36.jpg","thumbnail":"https://randomuser.me/api/portraits/thumb/men/36.jpg"},"location":{"street":{"number":6238,"name":"کوی نصر"},"city":"بابل","state":"کردستان","country":"Iran","postcode":30861,"coordinates":{"latitude":56.514,"longitude":51.0574},"timezone":{"offset":"+5:00","description":"Ekaterinburg, Islamabad, Karachi, Tashkent"}},"isactive":true}