{"gender":"female","name":{"title":"Mrs","first":"Siiri","last":"Annala"},"email":"siiri.annala@example.com","login":{"username":"goldensnake374","uuid":"Hgu9+Y9tTaaIyIfVqOCD4w==","isloggedin":true},"picture":{"large":"https://randomuser.me/api/portraits/women/67.jpg","medium":"https://randomuser.me/api/portraits/med/women/67.jpg","thumbnail":"https://randomuser.me/api/portraits/thumb/women/67.jpg"},"location":{"street":{"number":476,"name":"Pispalan Valtatie"},"city":"Tuusniemi","state":"Lapland","country":"Finland","postcode":77381,"coordinates":{"latitude":-76.771,"longitude":-109.0952},"timezone":{"offset":"+3:30","description":"Tehran"}},"isactive":false}