{"gender":"female","name":{"title":"Ms","first":"دینا","last":"رضاییان"},"email":"dyn.rdyyn@example.com","login":{"username":"silverbutterfly246","uuid":"D1uQPinpTbG2Q2k03SO2eg==","isloggedin":false},"picture":{"large":"https://randomuser.me/api/portraits/women/18.jpg","medium":"https://randomuser.me/api/portraits/med/women/18.jpg","thumbnail":"https://randomuser.me/api/portraits/thumb/women/18.jpg"},"location":{"street":{"number":5411,"name":"پیروزی"},"city":"کرمان","state":"سیستان و بلوچستان","country":"Iran","postcode":25181,"coordinates":{"latitude":78.7361,"longitude":99.1006},"timezone":{"offset":"+11:00","description":"Magadan, Solomon Islands, New Caledonia"}},"isactive":false}