{"gender":"male","name":{"title":"Mr","first":"Alexander","last":"Wong"},"email":"alexander.wong@example.com","login":{"username":"happyelephant481","uuid":"p2WapRdRQqmW8BQvSStdZg==","isloggedin":false},"picture":{"large":"https://randomuser.me/api/portraits/men/7.jpg","medium":"https://randomuser.me/api/portraits/med/men/7.jpg","thumbnail":"https://randomuser.me/api/portraits/thumb/men/7.jpg"},"location":{"street":{"number":4349,"name":"Park Rd"},"city":"Cumberland","state":"British Columbia","country":"Canada","postcode":"E9J 5V7","coordinates":{"latitude":20.7284,"longitude":-94.0699},"timezone":{"offset":"-3:00","description":"Brazil, Buenos Aires, Georgetown"}},"isactive":true}