{"gender":"female","name":{"title":"Miss","first":"Sally","last":"Wade"},"email":"sally.wade@example.com","login":{"username":"redgoose461","uuid":"aUafr7pyQ3iebsy8r4NFKg==","isloggedin":true},"picture":{"large":"https://randomuser.me/api/portraits/women/33.jpg","medium":"https://randomuser.me/api/portraits/med/women/33.jpg","thumbnail":"https://randomuser.me/api/portraits/thumb/women/33.jpg"},"location":{"street":{"number":9614,"name":"Lovers Ln"},"city":"Salinas","state":"Oregon","country":"United States","postcode":66379,"coordinates":{"latitude":-81.1792,"longitude":-119.2846},"timezone":{"offset":"+5:45","description":"Kathmandu"}},"isactive":false}