{"gender":"female","name":{"title":"Miss","first":"Victoria","last":"Kelly"},"email":"victoria.kelly@example.com","login":{"username":"smallgorilla546","uuid":"d3rqU9i8TCyGvWw9m9tAWQ==","isloggedin":false},"picture":{"large":"https://randomuser.me/api/portraits/women/22.jpg","medium":"https://randomuser.me/api/portraits/med/women/22.jpg","thumbnail":"https://randomuser.me/api/portraits/thumb/women/22.jpg"},"location":{"street":{"number":3256,"name":"Richmond Road"},"city":"Salford","state":"Hertfordshire","country":"United Kingdom","postcode":"C6 0XJ","coordinates":{"latitude":-8.6317,"longitude":-148.0294},"timezone":{"offset":"-3:30","description":"Newfoundland"}},"isactive":true}