{"gender":"male","name":{"title":"Mr","first":"Ramna","last":"da Luz"},"email":"ramna.daluz@example.com","login":{"username":"whitecat512","uuid":"SlOMbWVOQhWh0nQqTqvu5Q==","isloggedin":false},"picture":{"large":"https://randomuser.me/api/portraits/men/69.jpg","medium":"https://randomuser.me/api/portraits/med/men/69.jpg","thumbnail":"https://randomuser.me/api/portraits/thumb/men/69.jpg"},"location":{"street":{"number":3721,"name":"Rua Bela Vista "},"city":"Catanduva","state":"Maranhão","country":"Brazil","postcode":24124,"coordinates":{"latitude":-22.5609,"longitude":-108.7802},"timezone":{"offset":"-2:00","description":"Mid-Atlantic"}},"isactive":false}