{"gender":"female","name":{"title":"Mrs","first":"Irísia","last":"Moura"},"email":"irisia.moura@example.com","login":{"username":"orangezebra532","uuid":"VdXlgxULR+ywAAKEIp62Zg==","isloggedin":false},"picture":{"large":"https://randomuser.me/api/portraits/women/0.jpg","medium":"https://randomuser.me/api/portraits/med/women/0.jpg","thumbnail":"https://randomuser.me/api/portraits/thumb/women/0.jpg"},"location":{"street":{"number":4091,"name":"Rua São Francisco "},"city":"São Vicente","state":"Mato Grosso do Sul","country":"Brazil","postcode":25395,"coordinates":{"latitude":35.1972,"longitude":40.8263},"timezone":{"offset":"+9:00","description":"Tokyo, Seoul, Osaka, Sapporo, Yakutsk"}},"isactive":true}