{"gender":"male","name":{"title":"Mr","first":"Eduardo","last":"Van Londen"},"email":"eduardo.vanlonden@example.com","login":{"username":"goldenfish710","uuid":"AiWzC0EYS5meLHnbOtjnJg==","isloggedin":true},"picture":{"large":"https://randomuser.me/api/portraits/men/36.jpg","medium":"https://randomuser.me/api/portraits/med/men/36.jpg","thumbnail":"https://randomuser.me/api/portraits/thumb/men/36.jpg"},"location":{"street":{"number":5690,"name":"Bokt"},"city":"Wittelte","state":"Drenthe","country":"Netherlands","postcode":56964,"coordinates":{"latitude":-63.3667,"longitude":110.5687},"timezone":{"offset":"-4:00","description":"Atlantic Time (Canada), Caracas, La Paz"}},"isactive":true}