{"gender":"female","name":{"title":"Mademoiselle","first":"Carmen","last":"Bourgeois"},"email":"carmen.bourgeois@example.com","login":{"username":"lazygorilla428","uuid":"Zc4JFlFKS+iAYyF0PYFzOw==","isloggedin":true},"picture":{"large":"https://randomuser.me/api/portraits/women/69.jpg","medium":"https://randomuser.me/api/portraits/med/women/69.jpg","thumbnail":"https://randomuser.me/api/portraits/thumb/women/69.jpg"},"location":{"street":{"number":3233,"name":"Rue D'Abbeville"},"city":"Hirschthal","state":"Appenzell Innerrhoden","country":"Switzerland","postcode":9305,"coordinates":{"latitude":-64.0183,"longitude":-71.1349},"timezone":{"offset":"+3:30","description":"Tehran"}},"isactive":false}